{
    "lists":[
        {
            "name":"Description",
            "desc":"This defines a flex container; inline or block depending on the given value.It enables a flex context for all its direct childre"
        },
        {
            "name":"Abc",
            "desc":"Abc defines a flex container; inline or block depending on the given value.It enables a flex context for all its direct childre"
        },
        {
            "name":"SYZ",
            "desc":"XYZ defines a flex container; inline or block depending on the given value.It enables a flex context for all its direct childre"
        }        

    ]
}